{
    "ai-mil5.3.9:0.1_0": "Milindapañha",
    "ai-mil5.3.9:0.2_0": "Meṇḍakapañha",
    "ai-mil5.3.9:0.3_0": "Paṇāmitavagga",
    "ai-mil5.3.9:0.4_0": "9. Aggaggasamaṇapañha",
    "ai-mil5.3.9:1.1_0": "“When the Buddha spoke like this, he said,",
    "ai-mil5.3.9:1.2_0": "they’re an ascetic because of the ending of defilements.",
    "ai-mil5.3.9:1.3_0": "And he had spoken to him.",
    "ai-mil5.3.9:2.1_0": "‘First, when four things are developed,",
    "ai-mil5.3.9:2.2_0": "For you call the ascetic life!’",
    "ai-mil5.3.9:3.1_0": "There are four things that keep them safe and sound, and enjoyment.",
    "ai-mil5.3.9:3.2_0": "Now, all of them,",
    "ai-mil5.3.9:3.3_0": "If you’re lost by the ending of defilements, that don’t have even an ascetic.",
    "ai-mil5.3.9:3.4_0": "But if you have a discrimination, you must acknowledge it.”",
    "ai-mil5.3.9:4.1_0": "“Great king, the Buddha has spoken of the defilements.",
    "ai-mil5.3.9:4.2_0": "And he had spoken to him.",
    "ai-mil5.3.9:4.3_0": "‘First teachers have an ascetic, not a brahmin.’",
    "ai-mil5.3.9:4.4_0": "The Buddha said, “Great king, this is the consequence of those people.",
    "ai-mil5.3.9:4.5_0": "‘Nothing an absolute present to them, not an ascetic, not a true ascetic. For this is called “Realized One”.",
    "ai-mil5.3.9:5.1_0": "Of all the defilements that might be practicing for an ascetic, all of them is said to be the best of them all.",
    "ai-mil5.3.9:5.2_0": "The flowers of flax, jackal flowers, with flowers is said to be the best kind of flowers all fruits, and many kinds of flowers. And the flowers of flatulence is said to be the best kind of rain.",
    "ai-mil5.3.9:5.3_0": "In the same way, all the defilements of sensuality is practicing for you to be the best of them all.",
    "ai-mil5.3.9:6.1_0": "Whether all is said to be the best of all fine rice, the crooked sal trees is said to be the foremost of them all.",
    "ai-mil5.3.9:6.2_0": "In the same way, all the defilements of sensuality, desire to be reborn, and ignorance have ended all defilements.”",
    "ai-mil5.3.9:6.3_0": "“It’s good, Sir, that you should repeat what I have said.”",
    "ai-mil5.3.9:7.1_0": "The ninth sub-chapter on the best."
}