{
    "ai-tha-ap29:0.1_0": "Therāpadāna",
    "ai-tha-ap29:0.2_0": "Subhūtivagga",
    "ai-tha-ap29:0.3_0": "7 Pulinapūjakattheraapadāna",
    "ai-tha-ap29:1.1_0": "“Having Vipassī,",
    "ai-tha-ap29:1.2_0": "I went to Bodhi,",
    "ai-tha-ap29:1.3_0": "if she gives up an old family,",
    "ai-tha-ap29:1.4_0": "study, stained, eminent,",
    "ai-tha-ap29:2.1_0": "At most eons",
    "ai-tha-ap29:2.2_0": "from the Kambalas,",
    "ai-tha-ap29:2.3_0": "I’m not aware of any bad places",
    "ai-tha-ap29:2.4_0": "and the fruits reed.",
    "ai-tha-ap29:3.1_0": "These thirty eons",
    "ai-tha-ap29:3.2_0": "and was a king of men.",
    "ai-tha-ap29:3.3_0": "A great mass of fire",
    "ai-tha-ap29:3.4_0": "Mahāpajāpatī Gotamī.",
    "ai-tha-ap29:4.1_0": "Attaining the four kinds of textual analysis",
    "ai-tha-ap29:4.2_0": "and skeleton without flesh or blood,",
    "ai-tha-ap29:4.3_0": "I have realized the six kinds of direct knowledge,",
    "ai-tha-ap29:4.4_0": "and fulfilled the Buddha’s instructions.”",
    "ai-tha-ap29:5.1_0": "That is how these verses were recited by the senior venerable Pajjota.",
    "ai-tha-ap29:6.1_0": "and the seventh part of the senior monks."
}