{
    "atk-s0510a23:0_0": "like a turban, ginger, and laughing loudly.",
    "atk-s0510a23:10_1": "Having got the tendons, the dancers, and a plowshare in the position of a state of flowers. They pay respect to the Buddha, esteem, and venerate the Buddha.",
    "atk-s0510a23:10_2": "you should look down on others.",
    "atk-s0510a23:11_0": "Five Kinds of decase.",
    "atk-s0510a23:1_0": "problem, gentleness, and colorful; in the middle of the senior monks.",
    "atk-s0510a23:2_1": "She brought them to the first bank.",
    "atk-s0510a23:3_0": "as well as on the near shore.",
    "atk-s0510a23:3_1": "Having seen the drawbacks of the Buddha, they harnessed Māra, and his army, going for refuge to the Buddha, venerating him as they want. And when he sees the Buddha, of his minds confidence in him, and rude him of his mind.",
    "atk-s0510a23:4_0": "as well as on the bank of the river.",
    "atk-s0510a23:4_1": "Third: knives, and throne.",
    "atk-s0510a23:4_2": "and venerated by the head of the hair with dancestors.",
    "atk-s0510a23:5_1": "fourth year ...",
    "atk-s0510a23:6_1": "Five with a progress, a hut, and an alms-food.",
    "atk-s0510a23:6_2": "But time to time the bolts of roots, two, three, four, five, sixty, and tendons.",
    "atk-s0510a23:6_3": "but it belonged to the Buddha.",
    "atk-s0510a23:7_0": "Sixth Discourse on the sixth occasions.",
    "atk-s0510a23:8_1": "There were seven flowers of flowers:",
    "atk-s0510a23:9_1": "They presented with flowers in the forest grove of flowers,"
}