{
    "thig2.1:0.1_0": "Second: Mallik훮",
    "thig2.1:0.2_0": "The Book of the Twos",
    "thig2.1:0.3_0": "Vir큰pakkhas,",
    "thig2.1:1.1_0": "Nand훮, see this bag of bones as",
    "thig2.1:1.2_0": "diseased, filthy, rotten,",
    "thig2.1:1.3_0": "With your mind unified and serene,",
    "thig2.1:1.4_0": "unified, serene;",
    "thig2.1:2.1_0": "the signless, and the desireless,",
    "thig2.1:2.2_0": "give up the tendency to conceit;",
    "thig2.1:2.3_0": "having comprehended conceit,",
    "thig2.1:2.4_0": "you will live at peace.",
    "thig2.1:3.1_0": "That is how the Buddha regularly advised the senior nun Nand훮 with these verses."
}