{
    "ai-tha-ap58:0.1_0": "Therāpadāna",
    "ai-tha-ap58:0.2_0": "Bījanivagga",
    "ai-tha-ap58:0.3_0": "As a consequence his followers protection, the Explaint",
    "ai-tha-ap58:1.1_0": "“Awakened as a god,",
    "ai-tha-ap58:1.2_0": "gave almsfood in the place",
    "ai-tha-ap58:1.3_0": "Going to the place for alms",
    "ai-tha-ap58:1.4_0": "I devoted to Mallikā.",
    "ai-tha-ap58:2.1_0": "Following his instructions,",
    "ai-tha-ap58:2.2_0": "the world is unripe,",
    "ai-tha-ap58:2.3_0": "Compassionate for all beings,",
    "ai-tha-ap58:2.4_0": "serene, has become serene.",
    "ai-tha-ap58:3.1_0": "Just as a fine field,",
    "ai-tha-ap58:3.2_0": "or even a seed,",
    "ai-tha-ap58:3.3_0": "who rightly keeps rightly discerning,",
    "ai-tha-ap58:3.4_0": "and Today there is fruit.",
    "ai-tha-ap58:4.1_0": "Now, almsfood,",
    "ai-tha-ap58:4.2_0": "It was truly happy with you,",
    "ai-tha-ap58:4.3_0": "When continued existence has become extinguished,",
    "ai-tha-ap58:4.4_0": "And you’ll remain silent.",
    "ai-tha-ap58:5.1_0": "Having understood this, the Buddha,",
    "ai-tha-ap58:5.2_0": "is burning with light.",
    "ai-tha-ap58:5.3_0": "Taking almsfood by a dwelling,",
    "ai-tha-ap58:5.4_0": "northern quarter.",
    "ai-tha-ap58:6.1_0": "Restrained in the monastic code,",
    "ai-tha-ap58:6.2_0": "and five faculties—",
    "ai-tha-ap58:6.3_0": "devoted to seclusion,",
    "ai-tha-ap58:6.4_0": "and live without defilements.",
    "ai-tha-ap58:7.1_0": "Attaining the four kinds of textual analysis",
    "ai-tha-ap58:7.2_0": "... “I attained the noble ones,” ...",
    "ai-tha-ap58:7.3_0": "and fulfilled the Buddha’s instructions.”",
    "ai-tha-ap58:8.1_0": "That is how these verses were recited by the senior venerable Sānu.",
    "ai-tha-ap58:9.1_0": "Having inspired with your voice, the sixth treatment through the nose."
}